sabr/__init__.py
sabr/aln2hmm.py
sabr/cli.py
sabr/constants.py
sabr/edit_pdb.py
sabr/jax_backend.py
sabr/mpnn_embeddings.py
sabr/options.py
sabr/renumber.py
sabr/softalign_output.py
sabr/softaligner.py
sabr/util.py
sabr/assets/embeddings.npz
sabr/assets/mpnn_encoder.npz
ANARCI/__init__.py
ANARCI/anarci.py
ANARCI/schemes.py
softalign/ENCODING.py
softalign/END_TO_END_MODELS.py
softalign/Input_MPNN.py
softalign/LDDT_LOSS.py
softalign/Loss_functions.py
softalign/MPNN.py
softalign/SW.py
softalign/Score_align.py
softalign/__init__.py
softalign/search.py
softalign/utils.py
softalign/models/CONT_SFT_06_T_3_1.npz
softalign/models/CONT_SW_05_T_3_1.npz
softalign/models/v_48_002.npz
softalign/models/v_48_010.npz
softalign/models/v_48_020.npz
softalign/models/v_48_030.npz
sabr_kit-0.3.1.dist-info/METADATA
sabr_kit-0.3.1.dist-info/WHEEL
sabr_kit-0.3.1.dist-info/entry_points.txt
sabr_kit-0.3.1.dist-info/licenses/LICENSE
sabr_kit-0.3.1.dist-info/RECORD
