Metadata-Version: 2.4
Name: sabr-kit
Version: 0.3.1
Summary: Structure-based Antibody Renumbering
Project-URL: Homepage, https://github.com/delalamo/sabr
Project-URL: Issues, https://github.com/delalamo/sabr/issues
Author: Diego del Alamo
License: MIT License
License-File: LICENSE
Requires-Python: >=3.11
Requires-Dist: biopython>=1.85
Requires-Dist: click>=8.1
Requires-Dist: dm-haiku>=0.0.12
Requires-Dist: jax>=0.4.20
Requires-Dist: jaxlib>=0.4.20
Requires-Dist: numpy>=2.4
Requires-Dist: pandas>=2.2
Requires-Dist: scipy>=1.12
Provides-Extra: test
Requires-Dist: pytest-cov>=4.1; extra == 'test'
Requires-Dist: pytest>=7.0; extra == 'test'
